daplexer/__init__.py
daplexer/core.py
daplexer/data/1.txt
daplexer/data/10.txt
daplexer/data/11.txt
daplexer/data/2.txt
daplexer/data/3.txt
daplexer/data/4.txt
daplexer/data/5.txt
daplexer/data/6.txt
daplexer/data/7.txt
daplexer/data/8.txt
daplexer/data/9.txt
daplexer-3.2.4.dist-info/METADATA
daplexer-3.2.4.dist-info/WHEEL
daplexer-3.2.4.dist-info/top_level.txt
daplexer-3.2.4.dist-info/RECORD
